tsstats/__init__.py
tsstats/__main__.py
tsstats/client.py
tsstats/config.py
tsstats/events.py
tsstats/exceptions.py
tsstats/log.py
tsstats/logger.py
tsstats/template.py
tsstats/templates/index.jinja2
tsstats/templates/stats.jinja2
tsstats/tests/__init__.py
tsstats/tests/conftest.py
tsstats/tests/res/config.ini
tsstats/tests/res/id_map.json
tsstats/tests/res/test.log
tsstats/tests/res/test.log.groups
tsstats/tests/res/test.log.identmap_wrong_identifier
tsstats/tests/res/test.log.stopped
tsstats/tests/res/test.log.utf8
tsstats/tests/test_client.py
tsstats/tests/test_config.py
tsstats/tests/test_ident_map.py
tsstats/tests/test_log.py
tsstats/tests/test_template.py
tsstats/utils.py
tsstats-2.1.0.dist-info/WHEEL
tsstats-2.1.0.dist-info/LICENSE
tsstats-2.1.0.dist-info/METADATA
tsstats-2.1.0.dist-info/entry_points.txt
tsstats-2.1.0.dist-info/RECORD
