Metadata-Version: 2.1
Name: tsstats
Version: 2.1.0
Summary: A simple Teamspeak stats generator
License: MIT
Author: Thor77
Author-email: thor77@thor77.org
Requires-Python: >=3.10,<4.0
Classifier: License :: OSI Approved :: MIT License
Classifier: Programming Language :: Python :: 3
Classifier: Programming Language :: Python :: 3.10
Classifier: Programming Language :: Python :: 3.11
Requires-Dist: jinja2 (>=3.1.2,<4.0.0)
Requires-Dist: pendulum (>=2.1.2,<3.0.0)
